portndock/__init__.py
portndock/__main__.py
portndock/commands.py
portndock/core.py
portndock/docker_utils.py
portndock/main.py
portndock/process_utils.py
portndock/ui.py
portndock-1.0.4.dist-info/licenses/LICENSE
portndock-1.0.4.dist-info/METADATA
portndock-1.0.4.dist-info/WHEEL
portndock-1.0.4.dist-info/entry_points.txt
portndock-1.0.4.dist-info/top_level.txt
portndock-1.0.4.dist-info/RECORD
