Metadata-Version: 2.4
Name: portndock
Version: 1.0.4
Summary: Dev-focused port watcher/killer with Docker awareness and live TUI
Author-email: Marc Carlo Dy <dymarccarlo@yahoo.com>
License: MIT
Project-URL: Homepage, https://github.com/decentaro/portndock
Project-URL: Repository, https://github.com/decentaro/portndock
Project-URL: Issues, https://github.com/decentaro/portndock/issues
Keywords: port,process,docker,development,kill,terminal,tui
Classifier: Development Status :: 4 - Beta
Classifier: Intended Audience :: Developers
Classifier: License :: OSI Approved :: MIT License
Classifier: Operating System :: OS Independent
Classifier: Programming Language :: Python :: 3
Classifier: Programming Language :: Python :: 3.8
Classifier: Programming Language :: Python :: 3.9
Classifier: Programming Language :: Python :: 3.10
Classifier: Programming Language :: Python :: 3.11
Classifier: Programming Language :: Python :: 3.12
Classifier: Topic :: Software Development
Classifier: Topic :: System :: Networking
Classifier: Topic :: System :: Systems Administration
Classifier: Topic :: Terminals
Classifier: Environment :: Console
Requires-Python: >=3.8
License-File: LICENSE
Dynamic: license-file
